{
  "metrics": [
    {
      "id": "5d011dba642339052e7a6e9e",
      "name": "Train.loss"
    },
    {
      "id": "5d011dba642339052e7a6ea0",
      "name": "Train.accuracy"
    },
    {
      "id": "5d011dba642339052e7a6ea2",
      "name": "Train.recall.OFF"
    },
    {
      "id": "5d011dba642339052e7a6ea4",
      "name": "Train.recall.NOT"
    },
    {
      "id": "5d011dba642339052e7a6ea6",
      "name": "Train.precision.OFF"
    },
    {
      "id": "5d011dba642339052e7a6ea8",
      "name": "Train.precision.NOT"
    },
    {
      "id": "5d011dba642339052e7a6eaa",
      "name": "Train.f1.OFF"
    },
    {
      "id": "5d011dba642339052e7a6eac",
      "name": "Train.f1.NOT"
    },
    {
      "id": "5d011dc4642339052e7a6ee8",
      "name": "Validation.loss"
    },
    {
      "id": "5d011dc4642339052e7a6eea",
      "name": "Validation.accuracy"
    },
    {
      "id": "5d011dc4642339052e7a6eec",
      "name": "Validation.recall.OFF"
    },
    {
      "id": "5d011dc4642339052e7a6eee",
      "name": "Validation.recall.NOT"
    },
    {
      "id": "5d011dc4642339052e7a6ef0",
      "name": "Validation.precision.OFF"
    },
    {
      "id": "5d011dc4642339052e7a6ef2",
      "name": "Validation.precision.NOT"
    },
    {
      "id": "5d011dc4642339052e7a6ef4",
      "name": "Validation.f1.OFF"
    },
    {
      "id": "5d011dc4642339052e7a6ef6",
      "name": "Validation.f1.NOT"
    }
  ]
}